pytest_loguru/__init__.py
pytest_loguru/_version.py
pytest_loguru/plugin.py
pytest_loguru-0.4.0.dist-info/METADATA
pytest_loguru-0.4.0.dist-info/WHEEL
pytest_loguru-0.4.0.dist-info/entry_points.txt
pytest_loguru-0.4.0.dist-info/licenses/LICENSE
pytest_loguru-0.4.0.dist-info/RECORD
